bg_pyclient/__init__.py
bg_pyclient/corefile.py
bg_pyclient-0.0.2.dist-info/LICENSE
bg_pyclient-0.0.2.dist-info/METADATA
bg_pyclient-0.0.2.dist-info/WHEEL
bg_pyclient-0.0.2.dist-info/top_level.txt
bg_pyclient-0.0.2.dist-info/RECORD
