Metadata-Version: 2.1
Name: bg-pyclient
Version: 0.0.2
Summary: Python client for braingenix api
Author: jjose
Author-email: <jjose@carboncopies.com>
Keywords: python,neural,emulation
Classifier: Development Status :: 1 - Planning
Classifier: Intended Audience :: Developers
Classifier: Programming Language :: Python :: 3
Classifier: Operating System :: Unix
Classifier: Operating System :: MacOS :: MacOS X
Classifier: Operating System :: Microsoft :: Windows
License-File: LICENSE
